Metadata-Version: 2.1
Name: GetGender
Version: 0.3
Summary: Gets gender of russian names
Home-page: https://github.com/Pirantel23/GetGender
Download-URL: https://github.com/Pirantel23/GetGender/archive/refs/tags/v0.3.tar.gz
Author: Pirantel
Author-email: max420652@gmail.com
License: MIT
Keywords: GENDER,NAME
Classifier: Development Status :: 3 - Alpha
Classifier: Intended Audience :: Developers
Classifier: Topic :: Software Development :: Build Tools
Classifier: License :: OSI Approved :: MIT License
Classifier: Programming Language :: Python :: 3
Classifier: Programming Language :: Python :: 3.4
Classifier: Programming Language :: Python :: 3.5
Classifier: Programming Language :: Python :: 3.6
Classifier: Programming Language :: Python :: 3.7
Classifier: Programming Language :: Python :: 3.8
Classifier: Programming Language :: Python :: 3.9
Classifier: Programming Language :: Python :: 3.10
Classifier: Programming Language :: Python :: 3.11
License-File: LICENSE.txt
